checkjpy2hkd/__init__.py
checkjpy2hkd/__main__.py
checkjpy2hkd/checker.py
checkjpy2hkd/config.toml
checkjpy2hkd-0.1.1.dist-info/entry_points.txt
checkjpy2hkd-0.1.1.dist-info/WHEEL
checkjpy2hkd-0.1.1.dist-info/METADATA
checkjpy2hkd-0.1.1.dist-info/RECORD
