Metadata-Version: 2.1
Name: checkjpy2hkd
Version: 0.1.1
Summary: Check the latest JPY to HKD exchange rates
Home-page: https://github.com/alexcheng628/checkjpy2hkd
License: Proprietary
Keywords: exchange rate
Author: Alex Cheng
Author-email: alex28.biz@gmail.com
Maintainer: Alex Cheng
Maintainer-email: alex28.biz@gmail.com
Requires-Python: >=3.10,<4.0
Classifier: Development Status :: 1 - Planning
Classifier: License :: Other/Proprietary License
Classifier: Programming Language :: Python :: 3
Classifier: Programming Language :: Python :: 3.10
Classifier: Programming Language :: Python :: 3.11
Requires-Dist: requests (>=2.28.1,<3.0.0)
Requires-Dist: tomli (>=2.0.1,<3.0.0)
Project-URL: Documentation, https://github.com/alexcheng628/checkjpy2hkd
Project-URL: Repository, https://github.com/alexcheng628/checkjpy2hkd
